{
  "name": "TypeScript Development",
  "image": "mcr.microsoft.com/devcontainers/typescript-node:1-20-bullseye",
  "customizations": {
    "vscode": {
      "settings": {
        "editor.formatOnSave": true,
        "editor.defaultFormatter": "esbenp.prettier-vscode",
        "editor.codeActionsOnSave": {
          "source.fixAll.eslint": true
        }
      },
      "extensions": [
        "bradlc.vscode-tailwindcss",
        "dbaeumer.vscode-eslint",
        "esbenp.prettier-vscode",
        "github.codespaces",
        "github.copilot",
        "github.copilot-chat",
        "github.github-vscode-theme",
        "github.vscode-pull-request-github",
        "ms-ceintl.vscode-language-pack-ja",
        "oderwat.indent-rainbow",
        "shardulm94.trailing-spaces",
        "streetsidesoftware.code-spell-checker"
      ]
    }
  },
  "postStartCommand": "bash .devcontainer/list-extensions.sh"
}
